sparse_operation_kit/__init__.py
sparse_operation_kit/kit_lib.py
sparse_operation_kit/core/__init__.py
sparse_operation_kit/core/_version.py
sparse_operation_kit/core/context_scope.py
sparse_operation_kit/core/embedding_layer_handle.py
sparse_operation_kit/core/embedding_variable_v1.py
sparse_operation_kit/core/embedding_variable_v2.py
sparse_operation_kit/core/graph_keys.py
sparse_operation_kit/core/initialize.py
sparse_operation_kit/core/inplace_initializer.py
sparse_operation_kit/embeddings/__init__.py
sparse_operation_kit/embeddings/all2all_dense_embedding.py
sparse_operation_kit/embeddings/distributed_embedding.py
sparse_operation_kit/embeddings/embedding_ops.py
sparse_operation_kit/embeddings/get_embedding_op.py
sparse_operation_kit/embeddings/tf_distributed_embedding.py
sparse_operation_kit/experiment/__init__.py
sparse_operation_kit/experiment/communication.py
sparse_operation_kit/experiment/distributed_variable.py
sparse_operation_kit/experiment/dynamic_variable.py
sparse_operation_kit/experiment/lookup.py
sparse_operation_kit/experiment/optimizer.py
sparse_operation_kit/lib/libcore.so
sparse_operation_kit/lib/libembedding.so
sparse_operation_kit/lib/libsok_experiment.so
sparse_operation_kit/lib/libsok_unit_test.so
sparse_operation_kit/lib/libsparse_operation_kit.so
sparse_operation_kit/lib/libsparse_operation_kit_compat_ops.so
sparse_operation_kit/operations/__init__.py
sparse_operation_kit/operations/compat_ops_lib.py
sparse_operation_kit/optimizers/__init__.py
sparse_operation_kit/optimizers/adam.py
sparse_operation_kit/optimizers/base_optimizer.py
sparse_operation_kit/optimizers/optimizer.py
sparse_operation_kit/optimizers/utils.py
sparse_operation_kit/saver/Saver.py
sparse_operation_kit/saver/__init__.py
sparse_operation_kit/tf/__init__.py
sparse_operation_kit/tf/keras/__init__.py
sparse_operation_kit/tf/keras/mixed_precision/__init__.py
sparse_operation_kit/tf/keras/mixed_precision/loss_scale_optimizer.py
merlin_sok-1.1.4.dist-info/LICENSE.txt
merlin_sok-1.1.4.dist-info/METADATA
merlin_sok-1.1.4.dist-info/WHEEL
merlin_sok-1.1.4.dist-info/top_level.txt
merlin_sok-1.1.4.dist-info/RECORD
