Metadata-Version: 2.1
Name: merlin-sok
Version: 1.1.4
Summary: SparseOperationKit (SOK) is a python package wrapped GPU accelerated operations dedicated for sparse training / inference cases.
Home-page: https://github.com/NVIDIA-Merlin/HugeCTR/tree/master/sparse_operation_kit
Author: NVIDIA
Author-email: hugectr-dev@exchange.nvidia.com
License: Apache 2.0
Platform: Linux
Requires-Python: >=3
Provides-Extra: tensorflow
Requires-Dist: tensorflow (>=1.15) ; extra == 'tensorflow'
